funapi/__init__.py
fungoogle-0.0.1.dist-info/LICENSE
fungoogle-0.0.1.dist-info/METADATA
fungoogle-0.0.1.dist-info/WHEEL
fungoogle-0.0.1.dist-info/entry_points.txt
fungoogle-0.0.1.dist-info/top_level.txt
fungoogle-0.0.1.dist-info/RECORD
